{
 "app": "frappe_wms",
 "category": "Modules",
 "charts": [
  {
   "chart_name": "Warehouse Movements by Type",
   "label": "Warehouse Movements by Type"
  }
 ],
 "content": "[{\"id\":\"wms_sc_location_pick\",\"type\":\"shortcut\",\"data\":{\"shortcut_name\":\"Location Pick\",\"col\":3}},{\"id\":\"wms_sc_qc\",\"type\":\"shortcut\",\"data\":{\"shortcut_name\":\"WMS QC Check\",\"col\":3}},{\"id\":\"wms_sc_cross_dock\",\"type\":\"shortcut\",\"data\":{\"shortcut_name\":\"WMS Cross Dock\",\"col\":3}},{\"id\":\"wms_sc_cycle_count\",\"type\":\"shortcut\",\"data\":{\"shortcut_name\":\"WMS Cycle Count\",\"col\":3}},{\"id\":\"wms_header_status\",\"type\":\"header\",\"data\":{\"text\":\"<span class=\\\"h4\\\"><b>Operational Status</b></span>\",\"col\":12}},{\"id\":\"wms_nc_pending_qc\",\"type\":\"number_card\",\"data\":{\"number_card_name\":\"Pending QC Checks\",\"col\":4}},{\"id\":\"wms_nc_cross_dock\",\"type\":\"number_card\",\"data\":{\"number_card_name\":\"Cross-dock Pending\",\"col\":4}},{\"id\":\"wms_nc_locations\",\"type\":\"number_card\",\"data\":{\"number_card_name\":\"Active Storage Locations\",\"col\":4}},{\"id\":\"wms_chart_movements\",\"type\":\"chart\",\"data\":{\"chart_name\":\"Warehouse Movements by Type\",\"col\":12}},{\"id\":\"wms_header_operations\",\"type\":\"header\",\"data\":{\"text\":\"<span class=\\\"h4\\\"><b>Operations</b></span>\",\"col\":12}},{\"id\":\"wms_card_daily\",\"type\":\"card\",\"data\":{\"card_name\":\"Daily Operations\",\"col\":4}},{\"id\":\"wms_card_quality\",\"type\":\"card\",\"data\":{\"card_name\":\"Quality & Cross-dock\",\"col\":4}},{\"id\":\"wms_card_locations\",\"type\":\"card\",\"data\":{\"card_name\":\"Stock & Locations\",\"col\":4}},{\"id\":\"wms_card_setup\",\"type\":\"card\",\"data\":{\"card_name\":\"Setup\",\"col\":4}},{\"id\":\"wms_card_erpnext\",\"type\":\"card\",\"data\":{\"card_name\":\"ERPNext Stock Flow\",\"col\":4}},{\"id\":\"wms_card_reports\",\"type\":\"card\",\"data\":{\"card_name\":\"Reports\",\"col\":4}}]",
 "custom_blocks": [],
 "doctype": "Workspace",
 "extends": null,
 "extends_another_page": 0,
 "for_user": "",
 "hide_custom": 0,
 "icon": "package",
 "indicator_color": "blue",
 "is_hidden": 0,
 "label": "WMS",
 "links": [
  {
   "hidden": 0,
   "is_query_report": 0,
   "label": "Daily Operations",
   "link_count": 3,
   "onboard": 0,
   "type": "Card Break"
  },
  {
   "dependencies": "",
   "hidden": 0,
   "is_query_report": 0,
   "label": "Location Pick",
   "link_count": 0,
   "link_to": "Location Pick",
   "link_type": "DocType",
   "onboard": 1,
   "type": "Link"
  },
  {
   "dependencies": "",
   "hidden": 0,
   "is_query_report": 0,
   "label": "WMS Cycle Count",
   "link_count": 0,
   "link_to": "WMS Cycle Count",
   "link_type": "DocType",
   "onboard": 1,
   "type": "Link"
  },
  {
   "dependencies": "",
   "hidden": 0,
   "is_query_report": 0,
   "label": "Batch Location Movement",
   "link_count": 0,
   "link_to": "Batch Location Movement",
   "link_type": "DocType",
   "onboard": 0,
   "type": "Link"
  },
  {
   "hidden": 0,
   "is_query_report": 0,
   "label": "Quality & Cross-dock",
   "link_count": 2,
   "onboard": 0,
   "type": "Card Break"
  },
  {
   "dependencies": "",
   "hidden": 0,
   "is_query_report": 0,
   "label": "WMS QC Check",
   "link_count": 0,
   "link_to": "WMS QC Check",
   "link_type": "DocType",
   "onboard": 0,
   "type": "Link"
  },
  {
   "dependencies": "",
   "hidden": 0,
   "is_query_report": 0,
   "label": "WMS Cross Dock",
   "link_count": 0,
   "link_to": "WMS Cross Dock",
   "link_type": "DocType",
   "onboard": 0,
   "type": "Link"
  },
  {
   "hidden": 0,
   "is_query_report": 0,
   "label": "Stock & Locations",
   "link_count": 5,
   "onboard": 0,
   "type": "Card Break"
  },
  {
   "dependencies": "",
   "hidden": 0,
   "is_query_report": 0,
   "label": "Batch Location Stock",
   "link_count": 0,
   "link_to": "Batch Location Stock",
   "link_type": "DocType",
   "onboard": 1,
   "type": "Link"
  },
  {
   "dependencies": "",
   "hidden": 0,
   "is_query_report": 0,
   "label": "Storage Location",
   "link_count": 0,
   "link_to": "Storage Location",
   "link_type": "DocType",
   "onboard": 1,
   "type": "Link"
  },
  {
   "dependencies": "",
   "hidden": 0,
   "is_query_report": 0,
   "label": "WMS Zone",
   "link_count": 0,
   "link_to": "WMS Zone",
   "link_type": "DocType",
   "onboard": 0,
   "type": "Link"
  },
  {
   "dependencies": "Item",
   "hidden": 0,
   "is_query_report": 0,
   "label": "Batch",
   "link_count": 0,
   "link_to": "Batch",
   "link_type": "DocType",
   "onboard": 0,
   "type": "Link"
  },
  {
   "dependencies": "",
   "hidden": 0,
   "is_query_report": 0,
   "label": "Warehouse",
   "link_count": 0,
   "link_to": "Warehouse",
   "link_type": "DocType",
   "onboard": 0,
   "type": "Link"
  },
  {
   "hidden": 0,
   "is_query_report": 0,
   "label": "Setup",
   "link_count": 4,
   "onboard": 0,
   "type": "Card Break"
  },
  {
   "dependencies": "",
   "hidden": 0,
   "is_query_report": 0,
   "label": "WMS Settings",
   "link_count": 0,
   "link_to": "WMS Settings",
   "link_type": "DocType",
   "onboard": 0,
   "type": "Link"
  },
  {
   "dependencies": "",
   "hidden": 0,
   "is_query_report": 0,
   "label": "WMS Putaway Rule",
   "link_count": 0,
   "link_to": "WMS Putaway Rule",
   "link_type": "DocType",
   "onboard": 0,
   "type": "Link"
  },
  {
   "dependencies": "",
   "hidden": 0,
   "is_query_report": 0,
   "label": "Item",
   "link_count": 0,
   "link_to": "Item",
   "link_type": "DocType",
   "onboard": 0,
   "type": "Link"
  },
  {
   "dependencies": "",
   "hidden": 0,
   "is_query_report": 0,
   "label": "Item Group",
   "link_count": 0,
   "link_to": "Item Group",
   "link_type": "DocType",
   "onboard": 0,
   "type": "Link"
  },
  {
   "hidden": 0,
   "is_query_report": 0,
   "label": "ERPNext Stock Flow",
   "link_count": 4,
   "onboard": 0,
   "type": "Card Break"
  },
  {
   "dependencies": "Item, Supplier",
   "hidden": 0,
   "is_query_report": 0,
   "label": "Purchase Receipt",
   "link_count": 0,
   "link_to": "Purchase Receipt",
   "link_type": "DocType",
   "onboard": 0,
   "type": "Link"
  },
  {
   "dependencies": "Item",
   "hidden": 0,
   "is_query_report": 0,
   "label": "Pick List",
   "link_count": 0,
   "link_to": "Pick List",
   "link_type": "DocType",
   "onboard": 0,
   "type": "Link"
  },
  {
   "dependencies": "Item, Customer",
   "hidden": 0,
   "is_query_report": 0,
   "label": "Delivery Note",
   "link_count": 0,
   "link_to": "Delivery Note",
   "link_type": "DocType",
   "onboard": 0,
   "type": "Link"
  },
  {
   "dependencies": "Item",
   "hidden": 0,
   "is_query_report": 0,
   "label": "Stock Entry",
   "link_count": 0,
   "link_to": "Stock Entry",
   "link_type": "DocType",
   "onboard": 0,
   "type": "Link"
  },
  {
   "hidden": 0,
   "is_query_report": 0,
   "label": "Reports",
   "link_count": 6,
   "onboard": 0,
   "type": "Card Break"
  },
  {
   "dependencies": "",
   "hidden": 0,
   "is_query_report": 1,
   "label": "Location Pick Lines",
   "link_count": 0,
   "link_to": "Location Pick Lines",
   "link_type": "Report",
   "onboard": 0,
   "type": "Link"
  },
  {
   "dependencies": "",
   "hidden": 0,
   "is_query_report": 1,
   "label": "Location Stock Reconciliation",
   "link_count": 0,
   "link_to": "Location Stock Reconciliation",
   "link_type": "Report",
   "onboard": 0,
   "type": "Link"
  },
  {
   "dependencies": "",
   "hidden": 0,
   "is_query_report": 1,
   "label": "Zone Occupancy",
   "link_count": 0,
   "link_to": "Zone Occupancy",
   "link_type": "Report",
   "onboard": 0,
   "type": "Link"
  },
  {
   "dependencies": "",
   "hidden": 0,
   "is_query_report": 1,
   "label": "Customer Stock Overview",
   "link_count": 0,
   "link_to": "Customer Stock Overview",
   "link_type": "Report",
   "onboard": 0,
   "type": "Link"
  },
  {
   "dependencies": "",
   "hidden": 0,
   "is_query_report": 1,
   "label": "Pick Performance",
   "link_count": 0,
   "link_to": "Pick Performance",
   "link_type": "Report",
   "onboard": 0,
   "type": "Link"
  },
  {
   "dependencies": "",
   "hidden": 0,
   "is_query_report": 1,
   "label": "Inbound Outbound Volume",
   "link_count": 0,
   "link_to": "Inbound Outbound Volume",
   "link_type": "Report",
   "onboard": 0,
   "type": "Link"
  }
 ],
 "module": "WMS",
 "name": "WMS",
 "number_cards": [
  {
   "label": "Pending QC Checks",
   "number_card_name": "Pending QC Checks"
  },
  {
   "label": "Cross-dock Pending",
   "number_card_name": "Cross-dock Pending"
  },
  {
   "label": "Active Storage Locations",
   "number_card_name": "Active Storage Locations"
  }
 ],
 "parent_page": "",
 "public": 1,
 "quick_lists": [],
 "restrict_to_domain": "",
 "roles": [],
 "sequence_id": 7.1,
 "shortcuts": [
  {
   "color": "Blue",
   "format": "{} Open",
   "label": "Location Pick",
   "link_to": "Location Pick",
   "stats_filter": "{\"status\": \"Open\"}",
   "type": "DocType"
  },
  {
   "color": "Orange",
   "format": "{} Pending",
   "label": "WMS QC Check",
   "link_to": "WMS QC Check",
   "stats_filter": "{\"status\": \"Pending\"}",
   "type": "DocType"
  },
  {
   "color": "Purple",
   "format": "{} Pending",
   "label": "WMS Cross Dock",
   "link_to": "WMS Cross Dock",
   "stats_filter": "{\"status\": \"Pending\"}",
   "type": "DocType"
  },
  {
   "color": "Yellow",
   "format": "{} Open",
   "label": "WMS Cycle Count",
   "link_to": "WMS Cycle Count",
   "stats_filter": "{\"status\": [\"in\", [\"Draft\", \"In Progress\"]]}",
   "type": "DocType"
  }
 ],
 "title": "WMS",
 "type": "Workspace"
}
